imaplar/client.py
imaplar/imap.py
imaplar/policy.py
imaplar/schema.py
imaplar/shell.py
imaplar/version.py
imaplar-1.0.1.dist-info/LICENSE
imaplar-1.0.1.dist-info/METADATA
imaplar-1.0.1.dist-info/WHEEL
imaplar-1.0.1.dist-info/entry_points.txt
imaplar-1.0.1.dist-info/top_level.txt
imaplar-1.0.1.dist-info/RECORD
