Metadata-Version: 2.1
Name: imaplar
Version: 1.0.1
Summary: IMAP mailbox monitor
Home-page: https://github.com/MichaelPaddon/imaplar
Author: Michael Paddon
Author-email: michael@paddon.org
License: GPLv3+
Keywords: imap
Platform: UNKNOWN
Classifier: Programming Language :: Python :: 3
Classifier: Development Status :: 4 - Beta
Classifier: License :: OSI Approved :: GNU General Public License v3 or later (GPLv3+)
Classifier: Operating System :: OS Independent
Classifier: Topic :: Communications :: Email :: Filters
Classifier: Topic :: Communications :: Email :: Post-Office :: IMAP
Requires-Python: >=3.7
License-File: LICENSE
Requires-Dist: Cerberus
Requires-Dist: PyYaml
Requires-Dist: imapclient
Requires-Dist: tenacity
Requires-Dist: importlib-metadata ; python_version < "3.8"
